pulsex/__init__.py
pulsex/_types.py
pulsex/active_model.py
pulsex/active_stress.py
pulsex/cardiac_model.py
pulsex/compressibility.py
pulsex/exceptions.py
pulsex/functions.py
pulsex/holzapfelogden.py
pulsex/invariants.py
pulsex/kinematics.py
pulsex/linear_elastic.py
pulsex/material_model.py
pulsex-0.1.1.dist-info/LICENSE
pulsex-0.1.1.dist-info/METADATA
pulsex-0.1.1.dist-info/WHEEL
pulsex-0.1.1.dist-info/top_level.txt
pulsex-0.1.1.dist-info/RECORD
