Metadata-Version: 2.1
Name: pulsex
Version: 0.1.1
Summary: Next generation cardiac mechanics solver based on FEniCSx
Author-email: Henrik Finsberg <henriknf@simula.no>
License: Copyright 2022 Henrik Finsberg
Requires-Python: >=3.10.0
License-File: LICENSE
Requires-Dist: fenics-dolfinx
Provides-Extra: all
Requires-Dist: pulsex[test] ; extra == 'all'
Requires-Dist: pulsex[docs] ; extra == 'all'
Requires-Dist: pulsex[dev] ; extra == 'all'
Provides-Extra: dev
Requires-Dist: pdbpp ; extra == 'dev'
Requires-Dist: ipython ; extra == 'dev'
Requires-Dist: bump2version ; extra == 'dev'
Requires-Dist: pre-commit ; extra == 'dev'
Provides-Extra: docs
Requires-Dist: jupyter-book ; extra == 'docs'
Requires-Dist: jupytext ; extra == 'docs'
Provides-Extra: test
Requires-Dist: pytest ; extra == 'test'
Requires-Dist: pytest-cov ; extra == 'test'
